smart_cache_cleaner/__init__.py
smart_cache_cleaner/main.py
smart_cache_cleaner-0.2.0.dist-info/LICENSE
smart_cache_cleaner-0.2.0.dist-info/METADATA
smart_cache_cleaner-0.2.0.dist-info/WHEEL
smart_cache_cleaner-0.2.0.dist-info/entry_points.txt
smart_cache_cleaner-0.2.0.dist-info/top_level.txt
smart_cache_cleaner-0.2.0.dist-info/RECORD
