Metadata-Version: 2.1
Name: smart-cache-cleaner
Version: 0.2.0
Summary: A cross-platform utility for cleaning cache and temporary files
Home-page: https://github.com/M43K-10GBASE-SR/smart-cache-cleaner
Author: Sean Michael
Author-email: hommeunix@gmail.com
Classifier: Development Status :: 3 - Alpha
Classifier: Intended Audience :: End Users/Desktop
Classifier: License :: OSI Approved :: MIT License
Classifier: Operating System :: OS Independent
Classifier: Programming Language :: Python :: 3
Classifier: Programming Language :: Python :: 3.6
Classifier: Programming Language :: Python :: 3.7
Classifier: Programming Language :: Python :: 3.8
Classifier: Programming Language :: Python :: 3.9
Requires-Python: >=3.6
License-File: LICENSE
Requires-Dist: psutil
Requires-Dist: tqdm
